myxine/__init__.py
myxine/myxine.py
myxine_client-0.2.1.dist-info/LICENSE
myxine_client-0.2.1.dist-info/METADATA
myxine_client-0.2.1.dist-info/WHEEL
myxine_client-0.2.1.dist-info/top_level.txt
myxine_client-0.2.1.dist-info/RECORD
