Metadata-Version: 2.1
Name: myxine-client
Version: 0.2.1
Summary: A Python client for the Myxine GUI server.
Home-page: https://github.com/kwf/myxine
Author: Kenny Foner
Author-email: kwf@very.science
License: MIT
Platform: UNKNOWN
Classifier: License :: OSI Approved :: MIT License
Classifier: Programming Language :: Python
Classifier: Programming Language :: Python :: 3
Classifier: Programming Language :: Python :: 3.6
Classifier: Programming Language :: Python :: Implementation :: CPython
Classifier: Programming Language :: Python :: Implementation :: PyPy
Requires-Python: >=3.6.0
Requires-Dist: requests
Requires-Dist: semantic-version
